pymican/__init__.py
pymican/main.py
pymican/parse_result.py
pymican/bin/mican
pymican/bin/mican_x86_64_linux
pymican-1.8.0.data/scripts/mican
pymican-1.8.0.dist-info/LICENSE
pymican-1.8.0.dist-info/METADATA
pymican-1.8.0.dist-info/WHEEL
pymican-1.8.0.dist-info/top_level.txt
pymican-1.8.0.dist-info/RECORD
