Metadata-Version: 2.1
Name: pymican
Version: 1.8.0
Summary: Non-sequential protein structure alignment algorithm
Home-page: https://github.com/ShintaroMinami/mican
Author: Shintaro Minami
License: UNKNOWN
Platform: UNKNOWN
License-File: LICENSE
Requires-Dist: numpy
Requires-Dist: pandas
